mlflow/nemo/__init__.py
mlflow/nemo/cli.py
mlflow/nemo/search.py
mlflow_nemo-0.0.2.dist-info/METADATA
mlflow_nemo-0.0.2.dist-info/WHEEL
mlflow_nemo-0.0.2.dist-info/entry_points.txt
mlflow_nemo-0.0.2.dist-info/top_level.txt
mlflow_nemo-0.0.2.dist-info/RECORD
