Metadata-Version: 2.4
Name: mlflow-nemo
Version: 0.0.2
Summary: An MLflow plugin providing the 'nemo' CLI command
Requires-Dist: mlflow
